[
  {
    "address": {
      "unformatted": "כפר ידידיה, בבית העם",
      "location": {
        "lat": 32.3461657,
        "lng": 34.9000928
      },
      "formatted": "כפר ידידיה, ישראל",
      "city": "כפר ידידיה"
    },
    "times": [
      {
        "timestamp_start": "2024-06-24T14:30:00.000Z",
        "timestamp_end": "2024-06-24T18:30:00.000Z",
        "schedulingUrl": "https://bd.mda.org.il/#/pub-schedule/6EF8C216-969F-4B7A-AE6C-4E74BCB96682"
      }
    ]
  },
  {
    "address": {
      "unformatted": "ההגנה כרמיאל, מרכז מסחרי רמת רבין",
      "location": {
        "lat": 32.9034683,
        "lng": 35.2804229
      },
      "formatted": "ההגנה, כרמיאל, ישראל",
      "city": "כרמיאל"
    },
    "times": [
      {
        "timestamp_start": "2024-06-24T10:00:00.000Z",
        "timestamp_end": "2024-06-24T17:00:00.000Z",
        "schedulingUrl": "https://bd.mda.org.il/#/pub-schedule/3A0386BC-93D9-4D45-8548-137ABA606551"
      }
    ]
  },
  {
    "address": {
      "unformatted": "ירושלים, אולם עצמאות -מקסיקו אוני' הר הצופים ירושלים",
      "location": {
        "lat": 31.792754332037575,
        "lng": 35.24247119668841
      },
      "formatted": "ירושלים, ישראל",
      "city": "ירושלים"
    },
    "times": [
      {
        "timestamp_start": "2024-06-24T06:30:00.000Z",
        "timestamp_end": "2024-06-24T12:30:00.000Z",
        "schedulingUrl": "https://bd.mda.org.il/#/pub-schedule/25688DF2-E599-42A3-B252-6647C9DF3AC4"
      }
    ]
  },
  {
    "address": {
      "unformatted": "ירושלים, רח' המ\"ג 7 רוממה (תחנה נגישה), - תחנת מד\"א",
      "location": {
        "lat": 31.7913012,
        "lng": 35.1996146
      },
      "formatted": "מגן דוד אדום, המ\"ג 7, ירושלים, ישראל",
      "city": "ירושלים"
    },
    "times": [
      {
        "timestamp_start": "2024-06-24T06:00:00.000Z",
        "timestamp_end": "2024-06-24T14:00:00.000Z",
        "schedulingUrl": "https://bd.mda.org.il/#/pub-schedule/53ADBFA6-83D0-40F3-BEFB-0214D549E6C0"
      },
      {
        "timestamp_start": "2024-06-25T09:00:00.000Z",
        "timestamp_end": "2024-06-25T17:00:00.000Z",
        "schedulingUrl": "https://bd.mda.org.il/#/pub-schedule/8B975863-F480-431B-8702-7408CF8CA698"
      },
      {
        "timestamp_start": "2024-06-26T06:00:00.000Z",
        "timestamp_end": "2024-06-26T14:00:00.000Z",
        "schedulingUrl": "https://bd.mda.org.il/#/pub-schedule/7E3B2D75-696E-4DD0-8F0E-F099628258F9"
      },
      {
        "timestamp_start": "2024-06-27T06:00:00.000Z",
        "timestamp_end": "2024-06-27T14:00:00.000Z",
        "schedulingUrl": "https://bd.mda.org.il/#/pub-schedule/135995E7-04AC-412C-AF6F-DF5251AA816A"
      },
      {
        "timestamp_start": "2024-06-28T05:00:00.000Z",
        "timestamp_end": "2024-06-28T09:30:00.000Z",
        "schedulingUrl": "https://bd.mda.org.il/#/pub-schedule/FB08C855-ED0E-4B33-A727-31697CEA02E3"
      },
      {
        "timestamp_start": "2024-06-30T05:00:00.000Z",
        "timestamp_end": "2024-06-30T13:45:00.000Z",
        "schedulingUrl": "https://bd.mda.org.il/#/pub-schedule/1CE29FC6-52B5-4247-A848-E84A6CF3AB75"
      },
      {
        "timestamp_start": "2024-07-02T10:00:00.000Z",
        "timestamp_end": "2024-07-02T17:00:00.000Z",
        "schedulingUrl": "https://bd.mda.org.il/#/pub-schedule/28DEB488-8D2E-4D56-840D-E70804FAE963"
      },
      {
        "timestamp_start": "2024-07-05T05:00:00.000Z",
        "timestamp_end": "2024-07-05T09:30:00.000Z",
        "schedulingUrl": "https://bd.mda.org.il/#/pub-schedule/5F2CE96A-2ED2-4173-8626-A18B561D4201"
      },
      {
        "timestamp_start": "2024-07-07T05:00:00.000Z",
        "timestamp_end": "2024-07-07T13:45:00.000Z",
        "schedulingUrl": "https://bd.mda.org.il/#/pub-schedule/27759781-1CB2-4BCB-B007-ED5EA7494598"
      },
      {
        "timestamp_start": "2024-07-09T10:00:00.000Z",
        "timestamp_end": "2024-07-09T17:00:00.000Z",
        "schedulingUrl": "https://bd.mda.org.il/#/pub-schedule/0F5D8C1F-5039-4D88-BAAA-009D8E8C5893"
      },
      {
        "timestamp_start": "2024-07-12T05:00:00.000Z",
        "timestamp_end": "2024-07-12T09:30:00.000Z",
        "schedulingUrl": "https://bd.mda.org.il/#/pub-schedule/CEFD08D6-A85A-47E0-BFBA-36CC54ECB4A5"
      },
      {
        "timestamp_start": "2024-07-14T05:00:00.000Z",
        "timestamp_end": "2024-07-14T13:45:00.000Z",
        "schedulingUrl": "https://bd.mda.org.il/#/pub-schedule/9E254B95-1F1E-4A23-B2BF-33C52D75DE6D"
      },
      {
        "timestamp_start": "2024-07-16T10:00:00.000Z",
        "timestamp_end": "2024-07-16T17:00:00.000Z",
        "schedulingUrl": "https://bd.mda.org.il/#/pub-schedule/BD90C7FD-7B03-4463-B5F6-F7070409F4CB"
      },
      {
        "timestamp_start": "2024-07-19T05:00:00.000Z",
        "timestamp_end": "2024-07-19T09:30:00.000Z",
        "schedulingUrl": "https://bd.mda.org.il/#/pub-schedule/93E42FFD-5D48-42E8-8DEC-E5C71834A11A"
      },
      {
        "timestamp_start": "2024-07-21T05:00:00.000Z",
        "timestamp_end": "2024-07-21T13:45:00.000Z",
        "schedulingUrl": "https://bd.mda.org.il/#/pub-schedule/82740DA7-850B-4BFA-972C-B198BCDB7EE4"
      },
      {
        "timestamp_start": "2024-07-23T10:00:00.000Z",
        "timestamp_end": "2024-07-23T17:00:00.000Z",
        "schedulingUrl": "https://bd.mda.org.il/#/pub-schedule/55478031-BA7B-42BE-B9F3-13365449EE29"
      }
    ]
  },
  {
    "address": {
      "unformatted": "המלך ג'ורג' 20 ירושלים, משביר י-ם",
      "location": {
        "lat": 31.78153,
        "lng": 35.21602
      },
      "formatted": "המלך ג'ורג' 20, ירושלים, 9426208, ישראל",
      "city": "ירושלים"
    },
    "times": [
      {
        "timestamp_start": "2024-06-24T09:00:00.000Z",
        "timestamp_end": "2024-06-24T16:00:00.000Z",
        "schedulingUrl": "https://bd.mda.org.il/#/pub-schedule/1E253519-313F-48C7-A409-67578A7489CF"
      },
      {
        "timestamp_start": "2024-06-25T07:00:00.000Z",
        "timestamp_end": "2024-06-25T13:00:00.000Z",
        "schedulingUrl": "https://bd.mda.org.il/#/pub-schedule/0BD78D20-3FEA-41BF-90B8-D7499E464987"
      },
      {
        "timestamp_start": "2024-06-25T13:00:00.000Z",
        "timestamp_end": "2024-06-25T19:00:00.000Z",
        "schedulingUrl": "https://bd.mda.org.il/#/pub-schedule/2F17D204-9627-4F45-846F-726F78CE3FC5"
      },
      {
        "timestamp_start": "2024-06-26T07:00:00.000Z",
        "timestamp_end": "2024-06-26T13:30:00.000Z",
        "schedulingUrl": "https://bd.mda.org.il/#/pub-schedule/DF214FC1-F240-43AD-99D7-CD8B8BB40DB5"
      },
      {
        "timestamp_start": "2024-06-27T07:00:00.000Z",
        "timestamp_end": "2024-06-27T13:00:00.000Z",
        "schedulingUrl": "https://bd.mda.org.il/#/pub-schedule/5DCBD2AA-0A6E-418C-BD60-0BDB323E5BD6"
      },
      {
        "timestamp_start": "2024-06-27T13:00:00.000Z",
        "timestamp_end": "2024-06-27T19:00:00.000Z",
        "schedulingUrl": "https://bd.mda.org.il/#/pub-schedule/105D5CDA-6A81-4A1C-A9F0-A1C1BC6F4E48"
      },
      {
        "timestamp_start": "2024-06-28T06:00:00.000Z",
        "timestamp_end": "2024-06-28T09:45:00.000Z",
        "schedulingUrl": "https://bd.mda.org.il/#/pub-schedule/5CECA5CF-BE8D-417D-A578-6005B03C4741"
      }
    ]
  },
  {
    "address": {
      "unformatted": "חיפה, מרכז זיו נו\"ש + ליד דומינוס",
      "location": {
        "lat": 32.7829305,
        "lng": 35.0151513
      },
      "formatted": "מרכז זיו, חיפה, ישראל",
      "city": "חיפה"
    },
    "times": [
      {
        "timestamp_start": "2024-06-24T13:00:00.000Z",
        "timestamp_end": "2024-06-24T18:00:00.000Z",
        "schedulingUrl": "https://bd.mda.org.il/#/pub-schedule/26B0FA34-A40B-466C-A909-72DB36CA121F"
      },
      {
        "timestamp_start": "2024-06-24T06:30:00.000Z",
        "timestamp_end": "2024-06-24T12:30:00.000Z",
        "schedulingUrl": "https://bd.mda.org.il/#/pub-schedule/DCAFA187-65C8-40A9-A9BE-AB2013A92986"
      }
    ]
  },
  {
    "address": {
      "unformatted": "חיפה, מתחם קניות חוצות המפרץ - ליד גרג",
      "location": {
        "lat": 32.8092185,
        "lng": 35.0557838
      },
      "formatted": "החרושת 8, חיפה, ישראל",
      "city": "חיפה"
    },
    "times": [
      {
        "timestamp_start": "2024-06-24T06:30:00.000Z",
        "timestamp_end": "2024-06-24T12:30:00.000Z",
        "schedulingUrl": "https://bd.mda.org.il/#/pub-schedule/70EAB75F-7C7B-4EF1-8C23-1275DDDF27F4"
      },
      {
        "timestamp_start": "2024-06-28T05:30:00.000Z",
        "timestamp_end": "2024-06-28T10:30:00.000Z",
        "schedulingUrl": "https://bd.mda.org.il/#/pub-schedule/7855CE7B-4250-48AE-AF31-1ED6BBB6436D"
      }
    ]
  },
  {
    "address": {
      "unformatted": "העליה השניה 8 חיפה, בי\"ח רמב\"ם - קניון סגול",
      "location": {
        "lat": 32.8329875,
        "lng": 34.9857066
      },
      "formatted": "העלייה השנייה 8, חיפה, 3109601, ישראל",
      "city": "חיפה"
    },
    "times": [
      {
        "timestamp_start": "2024-06-24T06:00:00.000Z",
        "timestamp_end": "2024-06-24T12:30:00.000Z",
        "schedulingUrl": "https://bd.mda.org.il/#/pub-schedule/C8E7BE9E-FE68-483C-A10A-6295F09F21B7"
      },
      {
        "timestamp_start": "2024-06-25T06:00:00.000Z",
        "timestamp_end": "2024-06-25T12:30:00.000Z",
        "schedulingUrl": "https://bd.mda.org.il/#/pub-schedule/DFC14B39-0112-4DC7-A82B-0F34D38EFD13"
      }
    ]
  },
  {
    "address": {
      "unformatted": "עתיר ידע 9 כפר סבא, yael group",
      "location": {
        "lat": 32.1630592,
        "lng": 34.9318782
      },
      "formatted": "עתיר ידע 9, כפר סבא, ישראל",
      "city": "כפר סבא"
    },
    "times": [
      {
        "timestamp_start": "2024-06-24T07:00:00.000Z",
        "timestamp_end": "2024-06-24T12:00:00.000Z",
        "schedulingUrl": "https://bd.mda.org.il/#/pub-schedule/9E8FD448-725D-479C-BF59-FD18470E4C88"
      }
    ]
  },
  {
    "address": {
      "unformatted": "אפעל 35 פתח תקווה, בנין אדגר",
      "location": {
        "lat": 32.0982894,
        "lng": 34.84803
      },
      "formatted": "אפעל 35, פתח תקווה, ישראל",
      "city": "פתח תקווה"
    },
    "times": [
      {
        "timestamp_start": "2024-06-24T07:00:00.000Z",
        "timestamp_end": "2024-06-24T12:00:00.000Z",
        "schedulingUrl": "https://bd.mda.org.il/#/pub-schedule/0A5C8435-F487-469D-9C26-083A029F8A73"
      }
    ]
  },
  {
    "address": {
      "unformatted": "שדרות הרצל 133 רמלה, קריית מד\"א שרותי הדם רמלה(תחנה נגישה)",
      "location": {
        "lat": 31.923578436120685,
        "lng": 34.88001966776881
      },
      "formatted": "שדרות הרצל 133, רמלה, ישראל",
      "city": "רמלה"
    },
    "times": [
      {
        "timestamp_start": "2024-06-24T06:00:00.000Z",
        "timestamp_end": "2024-06-24T12:00:00.000Z",
        "schedulingUrl": "https://bd.mda.org.il/#/pub-schedule/03F72E15-97C6-4C25-8D70-23470A5650D1"
      },
      {
        "timestamp_start": "2024-06-25T10:00:00.000Z",
        "timestamp_end": "2024-06-25T17:00:00.000Z",
        "schedulingUrl": "https://bd.mda.org.il/#/pub-schedule/68377E70-1B6A-4995-AED4-9248FD5AAB30"
      },
      {
        "timestamp_start": "2024-07-01T06:00:00.000Z",
        "timestamp_end": "2024-07-01T12:00:00.000Z",
        "schedulingUrl": "https://bd.mda.org.il/#/pub-schedule/14732EB0-7E39-40C2-ACE6-CB7E8D81C3D7"
      },
      {
        "timestamp_start": "2024-07-02T06:00:00.000Z",
        "timestamp_end": "2024-07-02T12:00:00.000Z",
        "schedulingUrl": "https://bd.mda.org.il/#/pub-schedule/AF9B0BD9-2877-4BC7-B1FF-02B3939C2E05"
      },
      {
        "timestamp_start": "2024-07-03T06:00:00.000Z",
        "timestamp_end": "2024-07-03T12:00:00.000Z",
        "schedulingUrl": "https://bd.mda.org.il/#/pub-schedule/805266B3-9F64-491A-B7FE-ECA4074B122C"
      },
      {
        "timestamp_start": "2024-07-04T06:00:00.000Z",
        "timestamp_end": "2024-07-04T12:00:00.000Z",
        "schedulingUrl": "https://bd.mda.org.il/#/pub-schedule/4DBADD27-D6AB-462F-9BCF-BDDC14ACA661"
      },
      {
        "timestamp_start": "2024-07-05T05:00:00.000Z",
        "timestamp_end": "2024-07-05T09:30:00.000Z",
        "schedulingUrl": "https://bd.mda.org.il/#/pub-schedule/7020BF09-6BBB-4D19-92FC-27A92331F12E"
      },
      {
        "timestamp_start": "2024-07-07T06:00:00.000Z",
        "timestamp_end": "2024-07-07T12:00:00.000Z",
        "schedulingUrl": "https://bd.mda.org.il/#/pub-schedule/BA2E0C25-B35C-4AAF-840F-877AEA246EE7"
      },
      {
        "timestamp_start": "2024-07-08T06:00:00.000Z",
        "timestamp_end": "2024-07-08T12:00:00.000Z",
        "schedulingUrl": "https://bd.mda.org.il/#/pub-schedule/FC97F42E-F566-4C43-9E30-0681E359F62D"
      },
      {
        "timestamp_start": "2024-07-09T06:00:00.000Z",
        "timestamp_end": "2024-07-09T12:00:00.000Z",
        "schedulingUrl": "https://bd.mda.org.il/#/pub-schedule/DBA05BA5-7412-4FCF-9CC4-56ACB670E286"
      },
      {
        "timestamp_start": "2024-07-10T06:00:00.000Z",
        "timestamp_end": "2024-07-10T12:00:00.000Z",
        "schedulingUrl": "https://bd.mda.org.il/#/pub-schedule/47EBA9B6-6BEB-4668-B4E0-3905485DB689"
      },
      {
        "timestamp_start": "2024-07-11T06:00:00.000Z",
        "timestamp_end": "2024-07-11T12:00:00.000Z",
        "schedulingUrl": "https://bd.mda.org.il/#/pub-schedule/1CD72BB5-7A15-4D40-8A82-78BF0D3EE1F0"
      },
      {
        "timestamp_start": "2024-07-12T05:00:00.000Z",
        "timestamp_end": "2024-07-12T09:30:00.000Z",
        "schedulingUrl": "https://bd.mda.org.il/#/pub-schedule/5CD67E75-3D95-4326-8696-02BD50A3694A"
      },
      {
        "timestamp_start": "2024-07-14T06:00:00.000Z",
        "timestamp_end": "2024-07-14T12:00:00.000Z",
        "schedulingUrl": "https://bd.mda.org.il/#/pub-schedule/243D5A5B-EACE-4FA1-8984-2FC807DB2C76"
      },
      {
        "timestamp_start": "2024-07-15T06:00:00.000Z",
        "timestamp_end": "2024-07-15T12:00:00.000Z",
        "schedulingUrl": "https://bd.mda.org.il/#/pub-schedule/95009407-4482-4FC9-807D-A1222A5AFB01"
      },
      {
        "timestamp_start": "2024-07-16T06:00:00.000Z",
        "timestamp_end": "2024-07-16T12:00:00.000Z",
        "schedulingUrl": "https://bd.mda.org.il/#/pub-schedule/5748881A-A914-467B-AC77-72CF94145E42"
      },
      {
        "timestamp_start": "2024-07-17T06:00:00.000Z",
        "timestamp_end": "2024-07-17T12:00:00.000Z",
        "schedulingUrl": "https://bd.mda.org.il/#/pub-schedule/D1C93A70-F153-40CC-B7D2-631258A21A68"
      },
      {
        "timestamp_start": "2024-07-18T06:00:00.000Z",
        "timestamp_end": "2024-07-18T12:00:00.000Z",
        "schedulingUrl": "https://bd.mda.org.il/#/pub-schedule/E4715D6A-9C76-4BE3-8763-E96F7F108B4E"
      },
      {
        "timestamp_start": "2024-07-19T05:00:00.000Z",
        "timestamp_end": "2024-07-19T09:30:00.000Z",
        "schedulingUrl": "https://bd.mda.org.il/#/pub-schedule/94231688-7AC7-4A4A-8293-DFA8E71DB8C0"
      },
      {
        "timestamp_start": "2024-07-21T06:00:00.000Z",
        "timestamp_end": "2024-07-21T12:00:00.000Z",
        "schedulingUrl": "https://bd.mda.org.il/#/pub-schedule/839175A8-70E3-4559-B907-DA635F459C0C"
      },
      {
        "timestamp_start": "2024-07-22T06:00:00.000Z",
        "timestamp_end": "2024-07-22T12:00:00.000Z",
        "schedulingUrl": "https://bd.mda.org.il/#/pub-schedule/1B8B1B22-760E-46BA-9EDC-E3847D1A61D9"
      },
      {
        "timestamp_start": "2024-07-23T06:00:00.000Z",
        "timestamp_end": "2024-07-23T12:00:00.000Z",
        "schedulingUrl": "https://bd.mda.org.il/#/pub-schedule/5E665A54-85C2-4F2D-B7C9-EF6571231F98"
      },
      {
        "timestamp_start": "2024-07-24T06:00:00.000Z",
        "timestamp_end": "2024-07-24T12:00:00.000Z",
        "schedulingUrl": "https://bd.mda.org.il/#/pub-schedule/0F2F2481-1FA6-486A-9699-C558E19AB028"
      }
    ]
  },
  {
    "address": {
      "unformatted": "דרך שיבא רמת גן, בנק הדם מד\"א / בית חולים שיבא תל השומר (תחנה נגישה), - שרותי הדם מד\"א",
      "location": {
        "lat": 32.0459077,
        "lng": 34.8467524
      },
      "formatted": "בית חולים תל השומר, רמת גן, ישראל",
      "city": "רמת גן"
    },
    "times": [
      {
        "timestamp_start": "2024-06-24T05:00:00.000Z",
        "timestamp_end": "2024-06-24T11:30:00.000Z",
        "schedulingUrl": "https://bd.mda.org.il/#/pub-schedule/6DC57E93-93BB-44EB-ACBA-318E7DA5ED13"
      },
      {
        "timestamp_start": "2024-06-25T05:00:00.000Z",
        "timestamp_end": "2024-06-25T15:00:00.000Z",
        "schedulingUrl": "https://bd.mda.org.il/#/pub-schedule/74220571-F4E7-44DF-84EC-FD6F11A98A85"
      },
      {
        "timestamp_start": "2024-06-26T05:00:00.000Z",
        "timestamp_end": "2024-06-26T11:30:00.000Z",
        "schedulingUrl": "https://bd.mda.org.il/#/pub-schedule/2E8D5EF0-23D9-4F8F-A55F-29BD74EA055A"
      },
      {
        "timestamp_start": "2024-06-27T05:00:00.000Z",
        "timestamp_end": "2024-06-27T11:30:00.000Z",
        "schedulingUrl": "https://bd.mda.org.il/#/pub-schedule/104DD810-12BB-40B6-BA94-E6413B8C7C23"
      },
      {
        "timestamp_start": "2024-06-28T05:00:00.000Z",
        "timestamp_end": "2024-06-28T09:30:00.000Z",
        "schedulingUrl": "https://bd.mda.org.il/#/pub-schedule/4F1C7F7A-B705-4C37-B5DF-F8B5D919AFFA"
      },
      {
        "timestamp_start": "2024-06-30T05:00:00.000Z",
        "timestamp_end": "2024-06-30T11:30:00.000Z",
        "schedulingUrl": "https://bd.mda.org.il/#/pub-schedule/918E67A6-18DA-4D8C-B64C-88CE0363BF53"
      },
      {
        "timestamp_start": "2024-07-01T05:00:00.000Z",
        "timestamp_end": "2024-07-01T11:30:00.000Z",
        "schedulingUrl": "https://bd.mda.org.il/#/pub-schedule/9EAA8F13-7AC9-4C9D-83B9-FA1C922B2124"
      },
      {
        "timestamp_start": "2024-07-02T05:00:00.000Z",
        "timestamp_end": "2024-07-02T15:00:00.000Z",
        "schedulingUrl": "https://bd.mda.org.il/#/pub-schedule/03F76DBF-FE8E-426F-B8B7-862DE781CB37"
      },
      {
        "timestamp_start": "2024-07-03T05:00:00.000Z",
        "timestamp_end": "2024-07-03T11:30:00.000Z",
        "schedulingUrl": "https://bd.mda.org.il/#/pub-schedule/9A4A2BD4-EDF5-427D-8784-986A90619A17"
      },
      {
        "timestamp_start": "2024-07-04T05:00:00.000Z",
        "timestamp_end": "2024-07-04T11:30:00.000Z",
        "schedulingUrl": "https://bd.mda.org.il/#/pub-schedule/23AED00F-C3A4-420D-88F0-C52580FBC42E"
      },
      {
        "timestamp_start": "2024-07-05T05:00:00.000Z",
        "timestamp_end": "2024-07-05T09:30:00.000Z",
        "schedulingUrl": "https://bd.mda.org.il/#/pub-schedule/2095AAB7-9CEF-4BA2-AFF8-A6704B2271AC"
      },
      {
        "timestamp_start": "2024-07-07T05:00:00.000Z",
        "timestamp_end": "2024-07-07T11:30:00.000Z",
        "schedulingUrl": "https://bd.mda.org.il/#/pub-schedule/9AE9B53D-99D4-4305-94AC-F1770B273B70"
      },
      {
        "timestamp_start": "2024-07-08T05:00:00.000Z",
        "timestamp_end": "2024-07-08T11:30:00.000Z",
        "schedulingUrl": "https://bd.mda.org.il/#/pub-schedule/BCD9268B-1FF7-4820-B7EE-887B2D072076"
      },
      {
        "timestamp_start": "2024-07-09T05:00:00.000Z",
        "timestamp_end": "2024-07-09T15:00:00.000Z",
        "schedulingUrl": "https://bd.mda.org.il/#/pub-schedule/C4B5C1A8-8442-4066-A5D5-654B6623D987"
      },
      {
        "timestamp_start": "2024-07-10T05:00:00.000Z",
        "timestamp_end": "2024-07-10T11:30:00.000Z",
        "schedulingUrl": "https://bd.mda.org.il/#/pub-schedule/E211AEC0-8A1F-497E-A700-866ECEB28995"
      },
      {
        "timestamp_start": "2024-07-11T05:00:00.000Z",
        "timestamp_end": "2024-07-11T11:30:00.000Z",
        "schedulingUrl": "https://bd.mda.org.il/#/pub-schedule/4D78A965-7F05-4BA6-8956-CA2EFA3CD5FC"
      },
      {
        "timestamp_start": "2024-07-12T05:00:00.000Z",
        "timestamp_end": "2024-07-12T09:30:00.000Z",
        "schedulingUrl": "https://bd.mda.org.il/#/pub-schedule/CFA960FC-B4F1-463D-8A6E-F150B6DA7CB0"
      },
      {
        "timestamp_start": "2024-07-14T05:00:00.000Z",
        "timestamp_end": "2024-07-14T11:30:00.000Z",
        "schedulingUrl": "https://bd.mda.org.il/#/pub-schedule/3599E522-72B0-4F89-8230-82A0B028E3AB"
      },
      {
        "timestamp_start": "2024-07-15T05:00:00.000Z",
        "timestamp_end": "2024-07-15T11:30:00.000Z",
        "schedulingUrl": "https://bd.mda.org.il/#/pub-schedule/F39C2AD7-1AB7-4A5B-BF75-687E2A8774AB"
      },
      {
        "timestamp_start": "2024-07-16T05:00:00.000Z",
        "timestamp_end": "2024-07-16T15:00:00.000Z",
        "schedulingUrl": "https://bd.mda.org.il/#/pub-schedule/F6DE7DD6-3A26-4CAA-8D2F-69391AD00D80"
      },
      {
        "timestamp_start": "2024-07-17T05:00:00.000Z",
        "timestamp_end": "2024-07-17T11:30:00.000Z",
        "schedulingUrl": "https://bd.mda.org.il/#/pub-schedule/470E69C4-08A4-43F9-A062-A48DED355B48"
      },
      {
        "timestamp_start": "2024-07-18T05:00:00.000Z",
        "timestamp_end": "2024-07-18T11:30:00.000Z",
        "schedulingUrl": "https://bd.mda.org.il/#/pub-schedule/76DFF00F-408A-468D-A398-FF7A41B8DF21"
      },
      {
        "timestamp_start": "2024-07-19T05:00:00.000Z",
        "timestamp_end": "2024-07-19T09:30:00.000Z",
        "schedulingUrl": "https://bd.mda.org.il/#/pub-schedule/4724F56B-75E1-471C-A277-80FAB1D897F0"
      },
      {
        "timestamp_start": "2024-07-21T05:00:00.000Z",
        "timestamp_end": "2024-07-21T11:30:00.000Z",
        "schedulingUrl": "https://bd.mda.org.il/#/pub-schedule/62DA8B2C-0822-4BDC-9566-FB45122B1826"
      },
      {
        "timestamp_start": "2024-07-22T05:00:00.000Z",
        "timestamp_end": "2024-07-22T11:30:00.000Z",
        "schedulingUrl": "https://bd.mda.org.il/#/pub-schedule/39EBD371-FDD3-4CA1-AC69-D1CA6ABF9DC8"
      },
      {
        "timestamp_start": "2024-07-23T05:00:00.000Z",
        "timestamp_end": "2024-07-23T15:00:00.000Z",
        "schedulingUrl": "https://bd.mda.org.il/#/pub-schedule/FB37D33E-AC31-4773-B318-028037141BE1"
      },
      {
        "timestamp_start": "2024-07-24T05:00:00.000Z",
        "timestamp_end": "2024-07-24T11:30:00.000Z",
        "schedulingUrl": "https://bd.mda.org.il/#/pub-schedule/E54B4F38-C464-44BA-A21D-5614BBAF2CC3"
      }
    ]
  },
  {
    "address": {
      "unformatted": "שפרעם, ליד סופר פארם ובנק פועלים",
      "location": {
        "lat": 32.80576500000001,
        "lng": 35.169971
      },
      "formatted": "שפרעם, ישראל",
      "city": "שפרעם"
    },
    "times": [
      {
        "timestamp_start": "2024-06-24T06:00:00.000Z",
        "timestamp_end": "2024-06-24T12:30:00.000Z",
        "schedulingUrl": "https://bd.mda.org.il/#/pub-schedule/EFADD2A4-677F-4FBA-9629-8BAFB9029F0B"
      }
    ]
  },
  {
    "address": {
      "unformatted": "המשורר 27 רמת גן, שבט רעים",
      "location": {
        "lat": 32.0578046,
        "lng": 34.8491049
      },
      "formatted": "המשורר יעקב כהן 27, רמת גן, ישראל",
      "city": "רמת גן"
    },
    "times": [
      {
        "timestamp_start": "2024-06-25T14:00:00.000Z",
        "timestamp_end": "2024-06-25T18:00:00.000Z",
        "schedulingUrl": "https://bd.mda.org.il/#/pub-schedule/641E0D52-7B2B-4D67-82A6-D171CC04E91D"
      }
    ]
  },
  {
    "address": {
      "unformatted": "יוסף גדיש 1 עכו, מד\"א עכו",
      "location": {
        "lat": 32.924077,
        "lng": 35.0855535
      },
      "formatted": "יוסף גדיש 1, עכו, ישראל",
      "city": "עכו"
    },
    "times": [
      {
        "timestamp_start": "2024-06-25T06:15:00.000Z",
        "timestamp_end": "2024-06-25T12:30:00.000Z",
        "schedulingUrl": "https://bd.mda.org.il/#/pub-schedule/1636D189-8B8C-4518-A867-AAC7C3D3E130"
      }
    ]
  },
  {
    "address": {
      "unformatted": "משואות יצחק, ב\"מפגשים\"",
      "location": {
        "lat": 31.70261,
        "lng": 34.689968
      },
      "formatted": "משואות יצחק, ישראל",
      "city": "משואות יצחק"
    },
    "times": [
      {
        "timestamp_start": "2024-06-25T13:00:00.000Z",
        "timestamp_end": "2024-06-25T17:30:00.000Z",
        "schedulingUrl": "https://bd.mda.org.il/#/pub-schedule/A9BAD99F-D62F-44AD-AE37-75F7DE3CCAAF"
      }
    ]
  },
  {
    "address": {
      "unformatted": "אדורה, ישוב אדורה",
      "location": {
        "lat": 31.552219,
        "lng": 35.017634
      },
      "formatted": "אדורה",
      "city": "אדורה"
    },
    "times": [
      {
        "timestamp_start": "2024-06-25T11:00:00.000Z",
        "timestamp_end": "2024-06-25T16:00:00.000Z",
        "schedulingUrl": "https://bd.mda.org.il/#/pub-schedule/3E10A07F-AF23-495E-A78E-37BF25AA071D"
      }
    ]
  },
  {
    "address": {
      "unformatted": "דרך אבא חושי חיפה, בנין ראשי ליד קפה אגודה קומה 600",
      "location": {
        "lat": 32.7621909,
        "lng": 35.019002
      },
      "formatted": "חיפה, ישראל",
      "city": "חיפה"
    },
    "times": [
      {
        "timestamp_start": "2024-06-25T06:30:00.000Z",
        "timestamp_end": "2024-06-25T12:30:00.000Z",
        "schedulingUrl": "https://bd.mda.org.il/#/pub-schedule/108AB478-13B3-4BA9-BE63-BB341FB0A808"
      },
      {
        "timestamp_start": "2024-06-26T06:30:00.000Z",
        "timestamp_end": "2024-06-26T12:30:00.000Z",
        "schedulingUrl": "https://bd.mda.org.il/#/pub-schedule/8FE77CC2-FFAD-4B58-8861-0BB7C4D230F2"
      }
    ]
  },
  {
    "address": {
      "unformatted": "הושעיה, אר\"ת-מתחת לבית כנסת המרכזי",
      "location": {
        "lat": 32.7584354,
        "lng": 35.2864339
      },
      "formatted": "פאת שדה 22, הושעיה, ישראל",
      "city": "הושעיה"
    },
    "times": [
      {
        "timestamp_start": "2024-06-25T13:00:00.000Z",
        "timestamp_end": "2024-06-25T18:00:00.000Z",
        "schedulingUrl": "https://bd.mda.org.il/#/pub-schedule/3DC777A5-FA14-4BDA-9A6A-2644A6DFEB2A"
      }
    ]
  },
  {
    "address": {
      "unformatted": "ד.נ.משגב רקפת, מועדון",
      "location": {
        "lat": 32.856665,
        "lng": 35.2641255
      },
      "formatted": "רקפת, ישראל",
      "city": "רקפת"
    },
    "times": [
      {
        "timestamp_start": "2024-06-25T13:00:00.000Z",
        "timestamp_end": "2024-06-25T18:00:00.000Z",
        "schedulingUrl": "https://bd.mda.org.il/#/pub-schedule/C24064BC-35BE-4BF7-9FAF-C9E230642DFE"
      }
    ]
  },
  {
    "address": {
      "unformatted": "רם און, מקלט בית העם",
      "location": {
        "lat": 32.5287435,
        "lng": 35.2586585
      },
      "formatted": "רם און, ישראל",
      "city": "רם און"
    },
    "times": [
      {
        "timestamp_start": "2024-06-26T14:30:00.000Z",
        "timestamp_end": "2024-06-26T18:30:00.000Z",
        "schedulingUrl": "https://bd.mda.org.il/#/pub-schedule/4CA4B737-EB48-48B0-83EF-B95FC6BA38D7"
      }
    ]
  },
  {
    "address": {
      "unformatted": "שער מגנס ירושלים, בנין מנהלה אוני' הר הצופים גבעת רם",
      "location": {
        "lat": 31.7945578,
        "lng": 35.2414009
      },
      "formatted": "ירושלים",
      "city": "ירושלים"
    },
    "times": [
      {
        "timestamp_start": "2024-06-26T06:30:00.000Z",
        "timestamp_end": "2024-06-26T12:30:00.000Z",
        "schedulingUrl": "https://bd.mda.org.il/#/pub-schedule/EEFEC6E5-F918-40D8-B1A5-E0370AF89EBA"
      }
    ]
  },
  {
    "address": {
      "unformatted": "כיכר בן גוריון 1 קרית טבעון, במרכז ליד חומוס הארבעס",
      "location": {
        "lat": 32.722565,
        "lng": 35.1305159
      },
      "formatted": "בן גוריון 1, קרית טבעון, ישראל",
      "city": "קרית טבעון"
    },
    "times": [
      {
        "timestamp_start": "2024-06-26T12:00:00.000Z",
        "timestamp_end": "2024-06-26T17:30:00.000Z",
        "schedulingUrl": "https://bd.mda.org.il/#/pub-schedule/B2EFB533-A46B-485E-A332-B18564EEFB2F"
      }
    ]
  },
  {
    "address": {
      "unformatted": "קרית גת, יום בריאות - אמפיתיאטרון",
      "location": {
        "lat": 31.606757516878858,
        "lng": 34.77363924538131
      },
      "formatted": "קרית גת, ישראל",
      "city": "קרית גת"
    },
    "times": [
      {
        "timestamp_start": "2024-06-26T07:00:00.000Z",
        "timestamp_end": "2024-06-26T13:00:00.000Z",
        "schedulingUrl": "https://bd.mda.org.il/#/pub-schedule/F33707D7-B901-4670-9783-883713A2E45D"
      }
    ]
  },
  {
    "address": {
      "unformatted": "אורטל, מועדון",
      "location": {
        "lat": 33.086236,
        "lng": 35.758661
      },
      "formatted": "אורטל",
      "city": "אורטל"
    },
    "times": [
      {
        "timestamp_start": "2024-06-26T12:30:00.000Z",
        "timestamp_end": "2024-06-26T16:30:00.000Z",
        "schedulingUrl": "https://bd.mda.org.il/#/pub-schedule/8114340C-C910-448E-B026-A6E9E68A555B"
      }
    ]
  },
  {
    "address": {
      "unformatted": "שדרות טום לנטוס 31 נתניה, מרכז קהילתי קרית השרון",
      "location": {
        "lat": 32.3047454,
        "lng": 34.8699559
      },
      "formatted": "שדרות טום לנטוס 31, נתניה, ישראל",
      "city": "נתניה"
    },
    "times": [
      {
        "timestamp_start": "2024-06-26T13:00:00.000Z",
        "timestamp_end": "2024-06-26T18:00:00.000Z",
        "schedulingUrl": "https://bd.mda.org.il/#/pub-schedule/CCBCCA8F-8325-4824-AF92-A05B2D72DF9A"
      }
    ]
  },
  {
    "address": {
      "unformatted": "בית הערבה 12 ראשון לציון, גן אופירה נבון-קרית גנים",
      "location": {
        "lat": 31.807762,
        "lng": 35.476411
      },
      "formatted": "בית הערבה",
      "city": "ראשון לציון"
    },
    "times": [
      {
        "timestamp_start": "2024-06-26T13:00:00.000Z",
        "timestamp_end": "2024-06-26T18:00:00.000Z",
        "schedulingUrl": "https://bd.mda.org.il/#/pub-schedule/CD58EA78-1E9E-4BA8-AC27-1AE93DAE3BA2"
      }
    ]
  },
  {
    "address": {
      "unformatted": "יצחק בן צבי באר שבע, תחנה מרכזית",
      "location": {
        "lat": 31.24272051486917,
        "lng": 34.79787591574782
      },
      "formatted": "יצחק בן צבי, באר שבע, ישראל",
      "city": "באר שבע"
    },
    "times": [
      {
        "timestamp_start": "2024-06-26T06:00:00.000Z",
        "timestamp_end": "2024-06-26T12:30:00.000Z",
        "schedulingUrl": "https://bd.mda.org.il/#/pub-schedule/2B82481C-F654-4D27-9013-37D607D300FB"
      }
    ]
  },
  {
    "address": {
      "unformatted": "שקדיה 7 רמת גן, ביה\"ס גבעולים",
      "location": {
        "lat": 32.088675,
        "lng": 34.8122652
      },
      "formatted": "שקדיה 7, רמת גן, ישראל",
      "city": "רמת גן"
    },
    "times": [
      {
        "timestamp_start": "2024-06-27T13:00:00.000Z",
        "timestamp_end": "2024-06-27T18:00:00.000Z",
        "schedulingUrl": "https://bd.mda.org.il/#/pub-schedule/D2D97782-CBBD-4883-A1B6-9C82D1440487"
      }
    ]
  },
  {
    "address": {
      "unformatted": "אחיה, מועדון הישוב אחיה",
      "location": {
        "lat": 32.06093645236989,
        "lng": 35.32684959021713
      },
      "formatted": "bad_address",
      "city": ""
    },
    "times": [
      {
        "timestamp_start": "2024-06-27T15:30:00.000Z",
        "timestamp_end": "2024-06-27T19:30:00.000Z",
        "schedulingUrl": "https://bd.mda.org.il/#/pub-schedule/DEE1F8AB-C7CD-427B-9AB3-B71BE84AE1FB"
      }
    ]
  },
  {
    "address": {
      "unformatted": "אלעזר, מועדון הפיס ישוב אלעזר",
      "location": {
        "lat": 31.659676,
        "lng": 35.143074
      },
      "formatted": "אלעזר",
      "city": "אלעזר"
    },
    "times": [
      {
        "timestamp_start": "2024-06-27T14:00:00.000Z",
        "timestamp_end": "2024-06-27T19:00:00.000Z",
        "schedulingUrl": "https://bd.mda.org.il/#/pub-schedule/4C082563-7852-43AE-893D-6C89EB45F833"
      }
    ]
  },
  {
    "address": {
      "unformatted": "נתיבות, מועדון",
      "location": {
        "lat": 31.423132,
        "lng": 34.5946466
      },
      "formatted": "נתיבות, ישראל",
      "city": "נתיבות"
    },
    "times": [
      {
        "timestamp_start": "2024-06-27T11:00:00.000Z",
        "timestamp_end": "2024-06-27T15:30:00.000Z",
        "schedulingUrl": "https://bd.mda.org.il/#/pub-schedule/92943E5E-C249-4A7F-9E0E-CAB77AE68919"
      }
    ]
  },
  {
    "address": {
      "unformatted": "אדרת, בבית העם מושב אדרת",
      "location": {
        "lat": 31.6597169,
        "lng": 34.9944414
      },
      "formatted": "אדרת, ישראל",
      "city": "אדרת"
    },
    "times": [
      {
        "timestamp_start": "2024-06-27T14:00:00.000Z",
        "timestamp_end": "2024-06-27T19:00:00.000Z",
        "schedulingUrl": "https://bd.mda.org.il/#/pub-schedule/598CD29E-CCA6-4488-AED9-65478BE5BEC6"
      }
    ]
  },
  {
    "address": {
      "unformatted": "אמנון, מועדון פיס",
      "location": {
        "lat": 32.2420689,
        "lng": 35.4526342
      },
      "formatted": "בקעות",
      "city": "אמנון"
    },
    "times": [
      {
        "timestamp_start": "2024-06-27T13:30:00.000Z",
        "timestamp_end": "2024-06-27T17:30:00.000Z",
        "schedulingUrl": "https://bd.mda.org.il/#/pub-schedule/1E718670-EB83-4267-8A52-1354A9F4A7AB"
      }
    ]
  },
  {
    "address": {
      "unformatted": "דברת, מועדון לחברים",
      "location": {
        "lat": 32.6467305,
        "lng": 35.3500867
      },
      "formatted": "דברת, ישראל",
      "city": "דברת"
    },
    "times": [
      {
        "timestamp_start": "2024-06-27T13:00:00.000Z",
        "timestamp_end": "2024-06-27T17:30:00.000Z",
        "schedulingUrl": "https://bd.mda.org.il/#/pub-schedule/A6F81FAB-6A5E-4C88-A8C0-29B272DE3E93"
      }
    ]
  },
  {
    "address": {
      "unformatted": "כפר יחזקאל, מועדון עין טבעון",
      "location": {
        "lat": 32.566949,
        "lng": 35.360888
      },
      "formatted": "כפר יחזקאל, ישראל",
      "city": "כפר יחזקאל"
    },
    "times": [
      {
        "timestamp_start": "2024-06-27T13:00:00.000Z",
        "timestamp_end": "2024-06-27T17:00:00.000Z",
        "schedulingUrl": "https://bd.mda.org.il/#/pub-schedule/49674BAA-DA77-4B5D-8553-CEC0DB74A3B0"
      }
    ]
  },
  {
    "address": {
      "unformatted": "דרך המשי 23 גני תקווה, שבט גל",
      "location": {
        "lat": 32.0667307,
        "lng": 34.8677727
      },
      "formatted": "דרך המשי 23, גני תקווה, ישראל",
      "city": "גני תקווה"
    },
    "times": [
      {
        "timestamp_start": "2024-06-27T13:00:00.000Z",
        "timestamp_end": "2024-06-27T18:00:00.000Z",
        "schedulingUrl": "https://bd.mda.org.il/#/pub-schedule/F1713F78-8314-4257-9C90-6A1B894ED640"
      }
    ]
  },
  {
    "address": {
      "unformatted": "החשמונאים 75 קרית מוצקין, - תחנת מד\"א",
      "location": {
        "lat": 32.8440668,
        "lng": 35.0802042
      },
      "formatted": "77,, HaHashmona'im St 75, Kiryat Motskin, ישראל",
      "city": "קרית מוצקין"
    },
    "times": [
      {
        "timestamp_start": "2024-06-28T05:00:00.000Z",
        "timestamp_end": "2024-06-28T09:30:00.000Z",
        "schedulingUrl": "https://bd.mda.org.il/#/pub-schedule/D47DA361-B787-41AF-9200-3BE244B26982"
      },
      {
        "timestamp_start": "2024-07-05T05:00:00.000Z",
        "timestamp_end": "2024-07-05T09:30:00.000Z",
        "schedulingUrl": "https://bd.mda.org.il/#/pub-schedule/704CF134-A577-4FE7-A605-97CB09AAAFC4"
      },
      {
        "timestamp_start": "2024-07-12T05:00:00.000Z",
        "timestamp_end": "2024-07-12T09:30:00.000Z",
        "schedulingUrl": "https://bd.mda.org.il/#/pub-schedule/2E71A79C-B92A-43B7-93C9-9307AC9EA63D"
      },
      {
        "timestamp_start": "2024-07-19T05:00:00.000Z",
        "timestamp_end": "2024-07-19T09:30:00.000Z",
        "schedulingUrl": "https://bd.mda.org.il/#/pub-schedule/609BE6C2-5A87-473A-9E4B-AC6B9FE8F529"
      }
    ]
  },
  {
    "address": {
      "unformatted": "מינץ 7 נתניה, - תחנת מד\"א",
      "location": {
        "lat": 32.3284579,
        "lng": 34.8645215
      },
      "formatted": "בנימין מינץ 7, נתניה, ישראל",
      "city": "נתניה"
    },
    "times": [
      {
        "timestamp_start": "2024-06-28T05:30:00.000Z",
        "timestamp_end": "2024-06-28T09:30:00.000Z",
        "schedulingUrl": "https://bd.mda.org.il/#/pub-schedule/8B903EB7-1DD0-43CD-BC8D-C8878CCA8F04"
      },
      {
        "timestamp_start": "2024-07-05T05:30:00.000Z",
        "timestamp_end": "2024-07-05T09:30:00.000Z",
        "schedulingUrl": "https://bd.mda.org.il/#/pub-schedule/7F037902-D70B-4F07-98C3-6F5FE487C79F"
      },
      {
        "timestamp_start": "2024-07-12T05:30:00.000Z",
        "timestamp_end": "2024-07-12T09:30:00.000Z",
        "schedulingUrl": "https://bd.mda.org.il/#/pub-schedule/186FDB09-24DA-4057-BA6D-9DD62E38DFAB"
      },
      {
        "timestamp_start": "2024-07-19T05:30:00.000Z",
        "timestamp_end": "2024-07-19T09:30:00.000Z",
        "schedulingUrl": "https://bd.mda.org.il/#/pub-schedule/985EE32C-796B-40C1-8EAD-57D2C976A9E7"
      }
    ]
  },
  {
    "address": {
      "unformatted": "ביג יקנעם בכניסה",
      "location": {
        "lat": 32.6426784,
        "lng": 35.0927494
      },
      "formatted": "שדרות יצחק רבין 9, יוקנעם עילית, ישראל",
      "city": "ביג יקנעם בכניסה"
    },
    "times": [
      {
        "timestamp_start": "2024-06-28T05:00:00.000Z",
        "timestamp_end": "2024-06-28T10:00:00.000Z",
        "schedulingUrl": "https://bd.mda.org.il/#/pub-schedule/556FD9C4-2631-46EC-BCAA-D7A986FDE0B7"
      }
    ]
  },
  {
    "address": {
      "unformatted": "חיפה, רח' יצחק שדה 10 (תחנה נגישה), - תחנת מד\"א",
      "location": {
        "lat": 32.824678,
        "lng": 34.9882598
      },
      "formatted": "יצחק שדה 10, חיפה, ישראל",
      "city": "חיפה"
    },
    "times": [
      {
        "timestamp_start": "2024-06-28T05:00:00.000Z",
        "timestamp_end": "2024-06-28T09:30:00.000Z",
        "schedulingUrl": "https://bd.mda.org.il/#/pub-schedule/3CE9ADC0-8DFA-47DF-A585-53330E452D2F"
      },
      {
        "timestamp_start": "2024-07-05T05:00:00.000Z",
        "timestamp_end": "2024-07-05T09:30:00.000Z",
        "schedulingUrl": "https://bd.mda.org.il/#/pub-schedule/D9DF2FED-73E1-400D-AF84-D8D21262613A"
      },
      {
        "timestamp_start": "2024-07-12T05:00:00.000Z",
        "timestamp_end": "2024-07-12T09:30:00.000Z",
        "schedulingUrl": "https://bd.mda.org.il/#/pub-schedule/5E63E8CC-6B15-4B72-8257-AC040506D942"
      },
      {
        "timestamp_start": "2024-07-19T05:00:00.000Z",
        "timestamp_end": "2024-07-19T09:30:00.000Z",
        "schedulingUrl": "https://bd.mda.org.il/#/pub-schedule/1E35DEA2-1186-4419-9CDF-7065418C985A"
      }
    ]
  },
  {
    "address": {
      "unformatted": "אשדוד, רח' הרפואה 1 (תחנה נגישה), - תחנת מד\"א",
      "location": {
        "lat": 31.7799797,
        "lng": 34.654115
      },
      "formatted": "הרפואה 1, אשדוד, ישראל",
      "city": "אשדוד"
    },
    "times": [
      {
        "timestamp_start": "2024-06-28T05:00:00.000Z",
        "timestamp_end": "2024-06-28T09:30:00.000Z",
        "schedulingUrl": "https://bd.mda.org.il/#/pub-schedule/72160EF0-0E90-4E12-A881-B668ECFC2E4E"
      },
      {
        "timestamp_start": "2024-07-05T05:00:00.000Z",
        "timestamp_end": "2024-07-05T09:30:00.000Z",
        "schedulingUrl": "https://bd.mda.org.il/#/pub-schedule/5E57E44A-A4E5-481B-A072-055005C3CCEC"
      },
      {
        "timestamp_start": "2024-07-12T05:00:00.000Z",
        "timestamp_end": "2024-07-12T09:30:00.000Z",
        "schedulingUrl": "https://bd.mda.org.il/#/pub-schedule/3A4EADA7-75A4-4B89-80B5-86D6B379B15B"
      },
      {
        "timestamp_start": "2024-07-19T05:00:00.000Z",
        "timestamp_end": "2024-07-19T09:30:00.000Z",
        "schedulingUrl": "https://bd.mda.org.il/#/pub-schedule/5E9C7BC3-0037-48DD-AC7A-100F639BAF77"
      }
    ]
  },
  {
    "address": {
      "unformatted": "נהלל, מועדון ותיקים",
      "location": {
        "lat": 32.690807,
        "lng": 35.19609
      },
      "formatted": "נהלל, ישראל",
      "city": "נהלל"
    },
    "times": [
      {
        "timestamp_start": "2024-06-30T13:00:00.000Z",
        "timestamp_end": "2024-06-30T18:30:00.000Z",
        "schedulingUrl": "https://bd.mda.org.il/#/pub-schedule/C667B9B7-F850-4ED4-9983-7D27F100C03A"
      }
    ]
  },
  {
    "address": {
      "unformatted": "שדרות נים 2 ראשון לציון, מרכז עזריאלי ראשונים",
      "location": {
        "lat": 31.949533,
        "lng": 34.803047
      },
      "formatted": "שדרות נים 2, ראשון לציון, 7546302, ישראל",
      "city": "ראשון לציון"
    },
    "times": [
      {
        "timestamp_start": "2024-06-30T10:00:00.000Z",
        "timestamp_end": "2024-06-30T15:00:00.000Z",
        "schedulingUrl": "https://bd.mda.org.il/#/pub-schedule/B1E85C30-413C-4E93-8BDF-01F3926A8373"
      }
    ]
  },
  {
    "address": {
      "unformatted": "דוד רזיאל 1 רמלה, עזריאלי רמלה",
      "location": {
        "lat": 31.9257549,
        "lng": 34.8639629
      },
      "formatted": "שדרות דוד רזיאל 1, רמלה, ישראל",
      "city": "רמלה"
    },
    "times": [
      {
        "timestamp_start": "2024-06-30T11:00:00.000Z",
        "timestamp_end": "2024-06-30T16:00:00.000Z",
        "schedulingUrl": "https://bd.mda.org.il/#/pub-schedule/AA041EC9-01AC-4E56-B304-AA220B887776"
      }
    ]
  },
  {
    "address": {
      "unformatted": "פדואל, מועדון הישוב",
      "location": {
        "lat": 32.0822325,
        "lng": 35.0941143
      },
      "formatted": "ברוכין",
      "city": "פדואל"
    },
    "times": [
      {
        "timestamp_start": "2024-06-30T13:00:00.000Z",
        "timestamp_end": "2024-06-30T18:00:00.000Z",
        "schedulingUrl": "https://bd.mda.org.il/#/pub-schedule/A78F59F2-3C12-4E65-B279-9F9E739BE400"
      }
    ]
  },
  {
    "address": {
      "unformatted": "אודם, מועדון",
      "location": {
        "lat": 33.44852903890945,
        "lng": 32.05693494134149
      },
      "formatted": "bad_address",
      "city": ""
    },
    "times": [
      {
        "timestamp_start": "2024-06-30T13:30:00.000Z",
        "timestamp_end": "2024-06-30T17:30:00.000Z",
        "schedulingUrl": "https://bd.mda.org.il/#/pub-schedule/57D9967F-EAE1-4727-B2E7-672FFF0C5384"
      }
    ]
  },
  {
    "address": {
      "unformatted": "אשדות יעקב איחוד, בבית קרפ",
      "location": {
        "lat": 32.65877,
        "lng": 35.579637
      },
      "formatted": "אשדות יעקב איחוד, ישראל",
      "city": "אשדות יעקב איחוד"
    },
    "times": [
      {
        "timestamp_start": "2024-06-30T12:00:00.000Z",
        "timestamp_end": "2024-06-30T17:00:00.000Z",
        "schedulingUrl": "https://bd.mda.org.il/#/pub-schedule/687C9C90-0F2D-4F8F-984C-CBD2A82C77AB"
      }
    ]
  },
  {
    "address": {
      "unformatted": "קדרים, מרפאה",
      "location": {
        "lat": 32.898886,
        "lng": 35.471565
      },
      "formatted": "קדרים, ישראל",
      "city": "קדרים"
    },
    "times": [
      {
        "timestamp_start": "2024-06-30T12:00:00.000Z",
        "timestamp_end": "2024-06-30T17:00:00.000Z",
        "schedulingUrl": "https://bd.mda.org.il/#/pub-schedule/AF8E66B5-9852-43CB-A76C-70DFCC55B116"
      }
    ]
  },
  {
    "address": {
      "unformatted": "גן נר, מועדון הנוער מאחורי דורות בגלבוע",
      "location": {
        "lat": 32.53027170688493,
        "lng": 35.33538703452651
      },
      "formatted": "מועצה אזורית גלבוע, ד.נ. גלבוע, ישראל",
      "city": "גן נר"
    },
    "times": [
      {
        "timestamp_start": "2024-06-30T13:00:00.000Z",
        "timestamp_end": "2024-06-30T17:00:00.000Z",
        "schedulingUrl": "https://bd.mda.org.il/#/pub-schedule/C8EE0B3D-5BC7-46AE-99DE-3244AA282E11"
      }
    ]
  },
  {
    "address": {
      "unformatted": "מתנס גוש עציון - הגבעה הצהובה",
      "location": {
        "lat": 31.6584692,
        "lng": 35.1184861
      },
      "formatted": "אדום 34, אלון שבות",
      "city": "מתנס גוש עציון - הגבעה הצהובה"
    },
    "times": [
      {
        "timestamp_start": "2024-06-30T14:00:00.000Z",
        "timestamp_end": "2024-06-30T19:00:00.000Z",
        "schedulingUrl": "https://bd.mda.org.il/#/pub-schedule/B0D10733-8785-42A9-881E-F6D65FB03DDC"
      }
    ]
  },
  {
    "address": {
      "unformatted": "ירושלים, תרומת פלסמה AB, - תחנת מד\"א",
      "location": {
        "lat": 31.791749680874574,
        "lng": 35.199744756199166
      },
      "formatted": "ירושלים, ישראל",
      "city": "ירושלים"
    },
    "times": [
      {
        "timestamp_start": "2024-06-30T06:00:00.000Z",
        "timestamp_end": "2024-06-30T13:00:00.000Z",
        "schedulingUrl": "https://bd.mda.org.il/#/pub-schedule/5EE3319A-FB82-4206-9CD9-D5F00CDB4ACA"
      },
      {
        "timestamp_start": "2024-07-07T06:00:00.000Z",
        "timestamp_end": "2024-07-07T13:00:00.000Z",
        "schedulingUrl": "https://bd.mda.org.il/#/pub-schedule/9042AE20-8D7F-4FC9-A904-EBC29944FB80"
      },
      {
        "timestamp_start": "2024-07-14T06:00:00.000Z",
        "timestamp_end": "2024-07-14T13:00:00.000Z",
        "schedulingUrl": "https://bd.mda.org.il/#/pub-schedule/F3A84867-9B6D-44A6-B0A4-4D69B09C5C39"
      },
      {
        "timestamp_start": "2024-07-21T06:00:00.000Z",
        "timestamp_end": "2024-07-21T13:00:00.000Z",
        "schedulingUrl": "https://bd.mda.org.il/#/pub-schedule/217B98E0-60B1-49AB-A738-C816EBA758B9"
      }
    ]
  },
  {
    "address": {
      "unformatted": "הלילך 7 יבנה, מבנה בני עקיבא יבנה",
      "location": {
        "lat": 31.870348,
        "lng": 34.74622
      },
      "formatted": "הלילך 9, יבנה, ישראל",
      "city": "יבנה"
    },
    "times": [
      {
        "timestamp_start": "2024-07-01T13:00:00.000Z",
        "timestamp_end": "2024-07-01T18:00:00.000Z",
        "schedulingUrl": "https://bd.mda.org.il/#/pub-schedule/5636326F-DC9E-4617-AAEE-755DFC2E405C"
      }
    ]
  },
  {
    "address": {
      "unformatted": "מעלה עמוס, אולם שמחות",
      "location": {
        "lat": 31.596887,
        "lng": 35.22936500000001
      },
      "formatted": "מעלה עמוס",
      "city": "מעלה עמוס"
    },
    "times": [
      {
        "timestamp_start": "2024-07-01T14:00:00.000Z",
        "timestamp_end": "2024-07-01T19:00:00.000Z",
        "schedulingUrl": "https://bd.mda.org.il/#/pub-schedule/5F134605-FBE7-4517-BC44-EE17A2CEE4EB"
      }
    ]
  },
  {
    "address": {
      "unformatted": "יגאל אלון 98 תל אביב יפו, מגדל אמפא אלקטרה",
      "location": {
        "lat": 32.0700804,
        "lng": 34.7941446
      },
      "formatted": "יגאל אלון 98, תל אביב-יפו, ישראל",
      "city": "תל אביב יפו"
    },
    "times": [
      {
        "timestamp_start": "2024-07-01T07:00:00.000Z",
        "timestamp_end": "2024-07-01T12:00:00.000Z",
        "schedulingUrl": "https://bd.mda.org.il/#/pub-schedule/29272C3E-4F26-4777-A8ED-470FA52F2BFD"
      }
    ]
  },
  {
    "address": {
      "unformatted": "אלנבי 22 תל אביב יפו, מרכז רוחני וחברתי",
      "location": {
        "lat": 32.0730278,
        "lng": 34.7671179
      },
      "formatted": "אלנבי 22, תל אביב-יפו, ישראל",
      "city": "תל אביב יפו"
    },
    "times": [
      {
        "timestamp_start": "2024-07-02T13:00:00.000Z",
        "timestamp_end": "2024-07-02T18:00:00.000Z",
        "schedulingUrl": "https://bd.mda.org.il/#/pub-schedule/73E11D43-6D57-4932-A014-6B8A23E0FD41"
      }
    ]
  },
  {
    "address": {
      "unformatted": "הדודאים 6 חדרה, אולם ספורט קרית חינוך ע\"ש יצחק נבון",
      "location": {
        "lat": 32.431171,
        "lng": 34.8861803
      },
      "formatted": "חדרה, ישראל",
      "city": "חדרה"
    },
    "times": [
      {
        "timestamp_start": "2024-07-02T13:00:00.000Z",
        "timestamp_end": "2024-07-02T18:30:00.000Z",
        "schedulingUrl": "https://bd.mda.org.il/#/pub-schedule/B8F0EDF6-9C76-4ACD-8369-2AA6BF2798A4"
      }
    ]
  },
  {
    "address": {
      "unformatted": "כפר תפוח, גן ערמון",
      "location": {
        "lat": 32.117973,
        "lng": 35.249829
      },
      "formatted": "כפר תפוח",
      "city": "כפר תפוח"
    },
    "times": [
      {
        "timestamp_start": "2024-07-02T13:00:00.000Z",
        "timestamp_end": "2024-07-02T18:00:00.000Z",
        "schedulingUrl": "https://bd.mda.org.il/#/pub-schedule/13D90D11-3E58-490F-B258-B050DA2CD4CC"
      }
    ]
  },
  {
    "address": {
      "unformatted": "אמירים, בית העם",
      "location": {
        "lat": 32.9384469,
        "lng": 35.451642
      },
      "formatted": "הרימונים 6, אמירים, ישראל",
      "city": "אמירים"
    },
    "times": [
      {
        "timestamp_start": "2024-07-02T14:00:00.000Z",
        "timestamp_end": "2024-07-02T18:00:00.000Z",
        "schedulingUrl": "https://bd.mda.org.il/#/pub-schedule/C7E0D102-C914-4B3D-9C4D-D20B7BE35D52"
      }
    ]
  },
  {
    "address": {
      "unformatted": "לבון, גן תעשיה לבון",
      "location": {
        "lat": 32.942989,
        "lng": 35.282459
      },
      "formatted": "לבון, ישראל",
      "city": "לבון"
    },
    "times": [
      {
        "timestamp_start": "2024-07-02T06:00:00.000Z",
        "timestamp_end": "2024-07-02T12:30:00.000Z",
        "schedulingUrl": "https://bd.mda.org.il/#/pub-schedule/744EBAF9-10A2-410E-AB51-698167A8E709"
      }
    ]
  },
  {
    "address": {
      "unformatted": "סולם שונם, בכביש הראשי ליד המתנ\"ס",
      "location": {
        "lat": 32.60584665797892,
        "lng": 35.33446282553916
      },
      "formatted": "bad_address",
      "city": ""
    },
    "times": [
      {
        "timestamp_start": "2024-07-03T13:00:00.000Z",
        "timestamp_end": "2024-07-03T18:00:00.000Z",
        "schedulingUrl": "https://bd.mda.org.il/#/pub-schedule/A295E627-0BA7-4562-A8A6-01631C6293A1"
      }
    ]
  },
  {
    "address": {
      "unformatted": "ישיבת אלון שבות - כיתות מכללת הרצוג",
      "location": {
        "lat": 31.6580162,
        "lng": 35.1242561
      },
      "formatted": "אלון שבות",
      "city": "ישיבת אלון שבות - כיתות מכללת הרצוג"
    },
    "times": [
      {
        "timestamp_start": "2024-07-03T10:00:00.000Z",
        "timestamp_end": "2024-07-03T15:30:00.000Z",
        "schedulingUrl": "https://bd.mda.org.il/#/pub-schedule/D3A9018D-3D80-4A90-A48D-AE8FB7461910"
      }
    ]
  },
  {
    "address": {
      "unformatted": "גיניגר, חדר האוכל",
      "location": {
        "lat": 32.663419,
        "lng": 35.259861
      },
      "formatted": "גניגר, ישראל",
      "city": "גיניגר"
    },
    "times": [
      {
        "timestamp_start": "2024-07-04T13:00:00.000Z",
        "timestamp_end": "2024-07-04T17:00:00.000Z",
        "schedulingUrl": "https://bd.mda.org.il/#/pub-schedule/F6FFD702-68BF-45AF-80D7-32CFA2D11EF7"
      }
    ]
  },
  {
    "address": {
      "unformatted": "לוי אשכול 32 נתניה, מתנ\"ס גלי ים",
      "location": {
        "lat": 32.296505,
        "lng": 34.8461621
      },
      "formatted": "לוי אשכול 32, נתניה, 4242684, ישראל",
      "city": "נתניה"
    },
    "times": [
      {
        "timestamp_start": "2024-07-04T13:00:00.000Z",
        "timestamp_end": "2024-07-04T18:00:00.000Z",
        "schedulingUrl": "https://bd.mda.org.il/#/pub-schedule/6346C22F-CC6C-4B0A-B811-196F66F0FF55"
      }
    ]
  },
  {
    "address": {
      "unformatted": "עתיר ידע 5 ב כפר סבא, חברת אלבה",
      "location": {
        "lat": 32.1646432,
        "lng": 34.9298278
      },
      "formatted": "Atir Yeda St 5 ב, Kefar Sava, 4464305, ישראל",
      "city": "כפר סבא"
    },
    "times": [
      {
        "timestamp_start": "2024-07-04T07:00:00.000Z",
        "timestamp_end": "2024-07-04T12:00:00.000Z",
        "schedulingUrl": "https://bd.mda.org.il/#/pub-schedule/6C6F76F6-DC26-4CD5-81E7-39D12D36D137"
      }
    ]
  },
  {
    "address": {
      "unformatted": "היוגב, מועדון לחבר",
      "location": {
        "lat": 32.611036,
        "lng": 35.206391
      },
      "formatted": "היוגב, ישראל",
      "city": "היוגב"
    },
    "times": [
      {
        "timestamp_start": "2024-07-04T14:30:00.000Z",
        "timestamp_end": "2024-07-04T18:30:00.000Z",
        "schedulingUrl": "https://bd.mda.org.il/#/pub-schedule/235FB46B-099A-42D0-BAE1-4B838C25C5E8"
      }
    ]
  },
  {
    "address": {
      "unformatted": "עמיעד, מועדון",
      "location": {
        "lat": 32.930354,
        "lng": 35.54052100000001
      },
      "formatted": "עמיעד, ישראל",
      "city": "עמיעד"
    },
    "times": [
      {
        "timestamp_start": "2024-07-04T13:00:00.000Z",
        "timestamp_end": "2024-07-04T17:00:00.000Z",
        "schedulingUrl": "https://bd.mda.org.il/#/pub-schedule/04618260-6761-4F85-A06F-1CAA242EA52D"
      }
    ]
  },
  {
    "address": {
      "unformatted": "ירקונה, במתחם בית העם",
      "location": {
        "lat": 32.1434631,
        "lng": 34.8970693
      },
      "formatted": "הפרדס, ירקונה, ישראל",
      "city": "ירקונה"
    },
    "times": [
      {
        "timestamp_start": "2024-07-04T13:00:00.000Z",
        "timestamp_end": "2024-07-04T18:00:00.000Z",
        "schedulingUrl": "https://bd.mda.org.il/#/pub-schedule/7E8728C8-1072-4935-B934-ECFC2FE4C38D"
      }
    ]
  },
  {
    "address": {
      "unformatted": "שדי חמד, שדי חמד",
      "location": {
        "lat": 32.158488,
        "lng": 34.9428062
      },
      "formatted": "שדי חמד, ישראל",
      "city": "שדי חמד"
    },
    "times": [
      {
        "timestamp_start": "2024-07-04T14:00:00.000Z",
        "timestamp_end": "2024-07-04T18:00:00.000Z",
        "schedulingUrl": "https://bd.mda.org.il/#/pub-schedule/8E7DB415-0504-4B50-A4D9-F320FDE5D468"
      }
    ]
  },
  {
    "address": {
      "unformatted": "עין החורש, מועדון לחבר",
      "location": {
        "lat": 32.3858728,
        "lng": 34.9399951
      },
      "formatted": "עין החורש, ישראל",
      "city": "עין החורש"
    },
    "times": [
      {
        "timestamp_start": "2024-07-04T13:00:00.000Z",
        "timestamp_end": "2024-07-04T18:00:00.000Z",
        "schedulingUrl": "https://bd.mda.org.il/#/pub-schedule/8FDBC5C8-CB9D-4354-9AFD-E477DA1C8D0A"
      }
    ]
  },
  {
    "address": {
      "unformatted": "נחל דולב 16 בית שמש, מתנ\"ס גוונים רמת בית שמש א'",
      "location": {
        "lat": 31.7151352,
        "lng": 34.9961544
      },
      "formatted": "נחל דולב 16, בית שמש, ישראל",
      "city": "בית שמש"
    },
    "times": [
      {
        "timestamp_start": "2024-07-04T14:00:00.000Z",
        "timestamp_end": "2024-07-04T19:00:00.000Z",
        "schedulingUrl": "https://bd.mda.org.il/#/pub-schedule/0EB3E072-4CD5-4D6E-9A2F-B96D9DFF3EB6"
      }
    ]
  },
  {
    "address": {
      "unformatted": "אביאור 7 חדרה, תחנת מד\"א חדרה, - תחנת מד\"א",
      "location": {
        "lat": 32.4445161,
        "lng": 34.9228603
      },
      "formatted": "אביאור 7-11, חדרה, ישראל",
      "city": "חדרה"
    },
    "times": [
      {
        "timestamp_start": "2024-07-05T05:00:00.000Z",
        "timestamp_end": "2024-07-05T09:30:00.000Z",
        "schedulingUrl": "https://bd.mda.org.il/#/pub-schedule/D7811C1B-9B0E-43A6-B659-55254983EF35"
      }
    ]
  },
  {
    "address": {
      "unformatted": "באר שבע, במתנ\"ס ספורטיב שכונת רמות רח' הערים התאומות 20",
      "location": {
        "lat": 31.2806599,
        "lng": 34.7998167
      },
      "formatted": "שדרות הערים התאומות 20, באר שבע, ישראל",
      "city": "באר שבע"
    },
    "times": [
      {
        "timestamp_start": "2024-07-07T12:00:00.000Z",
        "timestamp_end": "2024-07-07T17:00:00.000Z",
        "schedulingUrl": "https://bd.mda.org.il/#/pub-schedule/30AE41B2-D6A3-459A-B56D-8BDA6CE8DDE1"
      }
    ]
  },
  {
    "address": {
      "unformatted": "אבן גבירול 69 תל אביב יפו, בנין העיריה - אולם אירועים ק\"12",
      "location": {
        "lat": 32.091274,
        "lng": 34.783026
      },
      "formatted": "שלמה אבן גבירול 166, תל אביב-יפו, ישראל",
      "city": "תל אביב יפו"
    },
    "times": [
      {
        "timestamp_start": "2024-07-07T06:30:00.000Z",
        "timestamp_end": "2024-07-07T12:00:00.000Z",
        "schedulingUrl": "https://bd.mda.org.il/#/pub-schedule/A1FEC599-C8AD-4F7F-A9A3-346C22E50996"
      }
    ]
  },
  {
    "address": {
      "unformatted": "שד יצחק רבין 10 ירושלים, מתחם סינימה סיטי בית נפש בנפש",
      "location": {
        "lat": 31.7827895,
        "lng": 35.2045759
      },
      "formatted": "שדרות יצחק רבין 10, ירושלים, 91950, ישראל",
      "city": "ירושלים"
    },
    "times": [
      {
        "timestamp_start": "2024-07-07T07:00:00.000Z",
        "timestamp_end": "2024-07-07T12:00:00.000Z",
        "schedulingUrl": "https://bd.mda.org.il/#/pub-schedule/4AEB5F6E-A035-492F-827B-23B7BF79492E"
      }
    ]
  },
  {
    "address": {
      "unformatted": "נחם, בית לחבר מושב נוחם",
      "location": {
        "lat": 31.76767079999999,
        "lng": 35.0024178
      },
      "formatted": "נחם, ישראל",
      "city": "נחם"
    },
    "times": [
      {
        "timestamp_start": "2024-07-07T14:00:00.000Z",
        "timestamp_end": "2024-07-07T19:00:00.000Z",
        "schedulingUrl": "https://bd.mda.org.il/#/pub-schedule/C5BDD368-9BDD-467F-8BCA-1ABA5D00A0EA"
      }
    ]
  },
  {
    "address": {
      "unformatted": "נטף, מבנה הקהילה החדש",
      "location": {
        "lat": 31.831276,
        "lng": 35.06957999999999
      },
      "formatted": "נטף, ישראל",
      "city": "נטף"
    },
    "times": [
      {
        "timestamp_start": "2024-07-07T14:00:00.000Z",
        "timestamp_end": "2024-07-07T19:00:00.000Z",
        "schedulingUrl": "https://bd.mda.org.il/#/pub-schedule/69EF192D-D8D9-4BD2-859A-7E1A13E2687A"
      }
    ]
  },
  {
    "address": {
      "unformatted": "מסד, מועדון חברים",
      "location": {
        "lat": 33.44852903890945,
        "lng": 32.05693494134149
      },
      "formatted": "bad_address",
      "city": ""
    },
    "times": [
      {
        "timestamp_start": "2024-07-07T13:00:00.000Z",
        "timestamp_end": "2024-07-07T17:00:00.000Z",
        "schedulingUrl": "https://bd.mda.org.il/#/pub-schedule/031D78E9-1619-4EF5-BD93-BE5B5BFC5261"
      }
    ]
  },
  {
    "address": {
      "unformatted": "ירושלים, בניין ג'נרי 2",
      "location": {
        "lat": 31.7831581,
        "lng": 35.2005671
      },
      "formatted": "בנק ישראל 7, ירושלים, ישראל",
      "city": "ירושלים"
    },
    "times": [
      {
        "timestamp_start": "2024-07-07T07:00:00.000Z",
        "timestamp_end": "2024-07-07T12:30:00.000Z",
        "schedulingUrl": "https://bd.mda.org.il/#/pub-schedule/2FCA50F8-91C3-4FE1-B27C-99A2EF1A016F"
      }
    ]
  },
  {
    "address": {
      "unformatted": "מירב, אולם נוף גלבוע",
      "location": {
        "lat": 32.452041,
        "lng": 35.422479
      },
      "formatted": "מירב, ישראל",
      "city": "מירב"
    },
    "times": [
      {
        "timestamp_start": "2024-07-07T13:00:00.000Z",
        "timestamp_end": "2024-07-07T18:00:00.000Z",
        "schedulingUrl": "https://bd.mda.org.il/#/pub-schedule/922B615F-0C2A-42A6-8997-F3C0630FD614"
      }
    ]
  },
  {
    "address": {
      "unformatted": "מגדל עוז, ישיבת מחניים מגדל עוז",
      "location": {
        "lat": 31.640932,
        "lng": 35.143139
      },
      "formatted": "מגדל עוז",
      "city": "מגדל עוז"
    },
    "times": [
      {
        "timestamp_start": "2024-07-08T11:00:00.000Z",
        "timestamp_end": "2024-07-08T16:00:00.000Z",
        "schedulingUrl": "https://bd.mda.org.il/#/pub-schedule/43CC2FB1-58E7-4A37-8102-1C888A17D6CE"
      }
    ]
  },
  {
    "address": {
      "unformatted": "ששת הימים 33 רעננה, בית הכנסת אריאל רעננה",
      "location": {
        "lat": 32.181837,
        "lng": 34.882891
      },
      "formatted": "ששת הימים 33, רעננה, ישראל",
      "city": "רעננה"
    },
    "times": [
      {
        "timestamp_start": "2024-07-08T13:30:00.000Z",
        "timestamp_end": "2024-07-08T18:30:00.000Z",
        "schedulingUrl": "https://bd.mda.org.il/#/pub-schedule/453EA9F5-1045-4B73-8426-1DD918D07FF1"
      }
    ]
  },
  {
    "address": {
      "unformatted": "נגוהות, מועדון ישוב נגוהות",
      "location": {
        "lat": 31.493077,
        "lng": 34.983347
      },
      "formatted": "נגוהות",
      "city": "נגוהות"
    },
    "times": [
      {
        "timestamp_start": "2024-07-09T14:00:00.000Z",
        "timestamp_end": "2024-07-09T19:00:00.000Z",
        "schedulingUrl": "https://bd.mda.org.il/#/pub-schedule/FC5D7A81-6103-4D1E-814A-1AA673A29A83"
      }
    ]
  },
  {
    "address": {
      "unformatted": "שדה נחום, מועדון",
      "location": {
        "lat": 32.525068,
        "lng": 35.480855
      },
      "formatted": "שדה נחום, ישראל",
      "city": "שדה נחום"
    },
    "times": [
      {
        "timestamp_start": "2024-07-10T13:00:00.000Z",
        "timestamp_end": "2024-07-10T17:00:00.000Z",
        "schedulingUrl": "https://bd.mda.org.il/#/pub-schedule/1F351AF7-4A79-4551-909A-2ECB936F0DAC"
      }
    ]
  },
  {
    "address": {
      "unformatted": "טירת צבי, במועדון",
      "location": {
        "lat": 32.422486,
        "lng": 35.52832
      },
      "formatted": "טירת צבי, ישראל",
      "city": "טירת צבי"
    },
    "times": [
      {
        "timestamp_start": "2024-07-10T13:00:00.000Z",
        "timestamp_end": "2024-07-10T17:00:00.000Z",
        "schedulingUrl": "https://bd.mda.org.il/#/pub-schedule/5D0813D9-41C8-475D-83C7-225A8E6E3B92"
      }
    ]
  },
  {
    "address": {
      "unformatted": "דייר חנא, אולם הספורט",
      "location": {
        "lat": 32.862316,
        "lng": 35.365253
      },
      "formatted": "דיר חנא, ישראל",
      "city": "דייר חנא"
    },
    "times": [
      {
        "timestamp_start": "2024-07-11T13:00:00.000Z",
        "timestamp_end": "2024-07-11T18:00:00.000Z",
        "schedulingUrl": "https://bd.mda.org.il/#/pub-schedule/47F24EEA-E7CF-4D48-8E66-1075E78A4F44"
      }
    ]
  },
  {
    "address": {
      "unformatted": "הר ברכה",
      "location": {
        "lat": 32.193264,
        "lng": 35.264885
      },
      "formatted": "ברכה",
      "city": "הר ברכה"
    },
    "times": [
      {
        "timestamp_start": "2024-07-11T13:00:00.000Z",
        "timestamp_end": "2024-07-11T18:00:00.000Z",
        "schedulingUrl": "https://bd.mda.org.il/#/pub-schedule/872A7592-0B47-41FB-AD51-8B3E74202BCF"
      }
    ]
  },
  {
    "address": {
      "unformatted": "עמק רפאים 47 ירושלים, בית חסיד",
      "location": {
        "lat": 31.762022,
        "lng": 35.2178564
      },
      "formatted": "עמק רפאים 47, ירושלים, ישראל",
      "city": "ירושלים"
    },
    "times": [
      {
        "timestamp_start": "2024-07-12T05:30:00.000Z",
        "timestamp_end": "2024-07-12T09:30:00.000Z",
        "schedulingUrl": "https://bd.mda.org.il/#/pub-schedule/32130D0E-FE04-49F0-88E9-0D8487A4A42C"
      }
    ]
  },
  {
    "address": {
      "unformatted": "בית הכרם 17 ירושלים, בית הכנסת הגדול בית הכרם",
      "location": {
        "lat": 31.7804981,
        "lng": 35.1908389
      },
      "formatted": "בית הכרם 17, ירושלים, ישראל",
      "city": "ירושלים"
    },
    "times": [
      {
        "timestamp_start": "2024-07-14T14:00:00.000Z",
        "timestamp_end": "2024-07-14T19:00:00.000Z",
        "schedulingUrl": "https://bd.mda.org.il/#/pub-schedule/86BD3EB3-D5E5-44F2-A399-A2120624AE91"
      }
    ]
  },
  {
    "address": {
      "unformatted": "רמת ישי, בית מרים",
      "location": {
        "lat": 32.7027076,
        "lng": 35.1661383
      },
      "formatted": "רמת ישי, ישראל",
      "city": "רמת ישי"
    },
    "times": [
      {
        "timestamp_start": "2024-07-15T14:00:00.000Z",
        "timestamp_end": "2024-07-15T18:30:00.000Z",
        "schedulingUrl": "https://bd.mda.org.il/#/pub-schedule/40E5400A-3F5C-4BC3-AA7B-E49E0A2810BC"
      }
    ]
  },
  {
    "address": {
      "unformatted": "סוקולוב 52 (בסוף הפסאז') רמת השרון, סניף ויצ\"ו רמה\"ש",
      "location": {
        "lat": 32.1439655,
        "lng": 34.8379397
      },
      "formatted": "סוקולוב 52, רמת השרון, ישראל",
      "city": "רמת השרון"
    },
    "times": [
      {
        "timestamp_start": "2024-07-23T13:00:00.000Z",
        "timestamp_end": "2024-07-23T18:00:00.000Z",
        "schedulingUrl": "https://bd.mda.org.il/#/pub-schedule/C6A1F66D-9398-4701-B500-7721D146F1BD"
      }
    ]
  }
]